fink_client/__init__.py
fink_client/avro_utils.py
fink_client/configuration.py
fink_client/consumer.py
fink_client/logger.py
fink_client/tester.py
fink_client/visualisation.py
fink_client/scripts/__init__.py
fink_client/scripts/fink_alert_viewer.py
fink_client/scripts/fink_client_register.py
fink_client/scripts/fink_consumer.py
fink_client/scripts/fink_datatransfer.py
fink_client-9.1.data/scripts/fink_client_test.sh
fink_client-9.1.dist-info/LICENSE
fink_client-9.1.dist-info/METADATA
fink_client-9.1.dist-info/WHEEL
fink_client-9.1.dist-info/entry_points.txt
fink_client-9.1.dist-info/top_level.txt
fink_client-9.1.dist-info/RECORD
