Metadata-Version: 2.1
Name: fink-client
Version: 9.1
Summary: Light-weight client to manipulate alerts from Fink
Home-page: https://fink-broker.readthedocs.io/en/latest/
Author: AstroLab Software
Author-email: peloton@lal.in2p3.fr
Project-URL: Documentation, https://fink-broker.readthedocs.io/en/latest/
Project-URL: Source, https://github.com/astrolabsoftware/fink-client
Classifier: Programming Language :: Python :: 3.9
Classifier: Programming Language :: Python :: 3.10
Classifier: License :: OSI Approved :: Apache Software License
Classifier: Operating System :: Unix
Classifier: Development Status :: 5 - Production/Stable
Classifier: Intended Audience :: Science/Research
License-File: LICENSE
Requires-Dist: astropy
Requires-Dist: confluent-kafka
Requires-Dist: coverage
Requires-Dist: coveralls
Requires-Dist: fastavro==1.9.4
Requires-Dist: matplotlib
Requires-Dist: numpy
Requires-Dist: pandas
Requires-Dist: pyarrow
Requires-Dist: PyYAML
Requires-Dist: tabulate
Requires-Dist: tqdm
Requires-Dist: psutil
